{
  "hash": "fcb28f7f",
  "configHash": "d58d8107",
  "lockfileHash": "f75bb817",
  "browserHash": "631cbab1",
  "optimized": {
    "react": {
      "src": "../../node_modules/react/index.js",
      "file": "react.js",
      "fileHash": "8cd99e92",
      "needsInterop": true
    },
    "react-dom/client": {
      "src": "../../node_modules/react-dom/client.js",
      "file": "react-dom_client.js",
      "fileHash": "e8080f2b",
      "needsInterop": true
    },
    "react-router-dom": {
      "src": "../../node_modules/react-router-dom/dist/index.mjs",
      "file": "react-router-dom.js",
      "fileHash": "ed2d7722",
      "needsInterop": false
    },
    "lucide-react": {
      "src": "../../node_modules/lucide-react/dist/esm/lucide-react.js",
      "file": "lucide-react.js",
      "fileHash": "548cc043",
      "needsInterop": false
    }
  },
  "chunks": {
    "chunk-YBFRUR3B": {
      "file": "chunk-YBFRUR3B.js"
    },
    "chunk-JRE55LYH": {
      "file": "chunk-JRE55LYH.js"
    }
  }
}